lambda_handler/__init__.py
lambda_handler/dependencies.py
lambda_handler/handler.py
lambda_handler/model/__init__.py
lambda_handler/model/base.py
lambda_handler/model/direct_invocation.py
lambda_handler/model/event_bridge.py
lambda_handler/model/s3.py
lambda_handler/model/sns.py
lambda_handler/model/sqs.py
lambda_handler/py.typed
lambda_handler/types.py
lambda_handler/utils.py
lambda_handler-2.0.0.dist-info/LICENSE
lambda_handler-2.0.0.dist-info/METADATA
lambda_handler-2.0.0.dist-info/WHEEL
lambda_handler-2.0.0.dist-info/RECORD
