Metadata-Version: 2.1
Name: lambda-handler
Version: 2.0.0
Summary: A Python package for routing and validating AWS events inside a Lambda function
Home-page: https://github.com/branchenergy/lambda-handler
License: Apache 2.0
Author: Matthew Badger
Author-email: matt@branchenergy.com
Requires-Python: >=3.10,<4.0
Classifier: License :: Other/Proprietary License
Classifier: Programming Language :: Python :: 3
Classifier: Programming Language :: Python :: 3.10
Classifier: Programming Language :: Python :: 3.11
Provides-Extra: fastapi
Requires-Dist: pydantic (>=1.10.2,<2.0.0)
Requires-Dist: typing-extensions (>=4.7.1,<5.0.0)
Project-URL: Repository, https://github.com/branchenergy/lambda-handler
